stm_layout/__init__.py
stm_layout/chip_db.py
stm_layout/chip_package.py
stm_layout/chip_stm.py
stm_layout/stm_layout.py
stm_layout/stm_layout_tk.py
stm_layout/tk/__init__.py
stm_layout/tk/tk_bga.py
stm_layout/tk/tk_elems.py
stm_layout/tk/tk_lqfp.py
stm_layout/tk/tk_tssop.py
stm_layout/tk/tk_workspace.py
stm_layout-0.1.4.dist-info/LICENSE
stm_layout-0.1.4.dist-info/METADATA
stm_layout-0.1.4.dist-info/WHEEL
stm_layout-0.1.4.dist-info/entry_points.txt
stm_layout-0.1.4.dist-info/top_level.txt
stm_layout-0.1.4.dist-info/RECORD
