Metadata-Version: 2.1
Name: stm-layout
Version: 0.1.4
Summary: Curses-based tool for configuring STM32 pins.
Home-page: https://github.com/tgree/stm_layout
Author: Terry Greeniaus
Author-email: terrygreeniaus@gmail.com
License: License :: OSI Approved :: MIT License
Keywords: stm32 modm-devices pin pinout
Platform: UNKNOWN
Classifier: Operating System :: POSIX
Classifier: Programming Language :: Python :: 3
Classifier: License :: OSI Approved :: MIT License
Requires-Python: >=3.6
License-File: LICENSE
Requires-Dist: modm-devices
Requires-Dist: tgcurses
